pytica/__init__.py
pytica/attendance.py
pytica/gradebook.py
pytica/insights.py
pytica/report.py
pytica/visualizer.py
pytica-0.2.2.dist-info/licenses/LICENSE
pytica-0.2.2.dist-info/METADATA
pytica-0.2.2.dist-info/WHEEL
pytica-0.2.2.dist-info/top_level.txt
pytica-0.2.2.dist-info/RECORD
