Metadata-Version: 2.4
Name: pytica
Version: 0.2.2
Summary: Python Learning Analytics Toolkit for Teachers and Schools
Home-page: https://github.com/bjaspel63/pytica
Author: Jaspel Bosales
Author-email: Jaspel Bosales <bjaspel63@gmail.com>
License: MIT
Project-URL: Homepage, https://github.com/bjaspel63/pytica
Requires-Python: >=3.8
License-File: LICENSE
Requires-Dist: pandas>=1.5.0
Requires-Dist: matplotlib>=3.7.0
Requires-Dist: openpyxl>=3.1.0
Dynamic: author
Dynamic: home-page
Dynamic: license-file
Dynamic: requires-python
